gradio_creditspanel/__init__.py
gradio_creditspanel/creditspanel.py
gradio_creditspanel/creditspanel.pyi
gradio_creditspanel/templates/component/index.js
gradio_creditspanel/templates/component/style.css
gradio_creditspanel/templates/example/index.js
gradio_creditspanel/templates/example/style.css
gradio_creditspanel-0.0.6.dist-info/METADATA
gradio_creditspanel-0.0.6.dist-info/WHEEL
gradio_creditspanel-0.0.6.dist-info/RECORD
