Metadata-Version: 2.4
Name: gradio_creditspanel
Version: 0.0.6
Summary: Credits Panel for Gradio UI
Author-email: Eliseu Silva <elismasilva@gmail.com>
License-Expression: Apache-2.0
Keywords: gradio-custom-component,gradio-template-HTML
Classifier: Development Status :: 3 - Alpha
Classifier: Operating System :: OS Independent
Classifier: Programming Language :: Python :: 3
Classifier: Programming Language :: Python :: 3 :: Only
Classifier: Programming Language :: Python :: 3.8
Classifier: Programming Language :: Python :: 3.9
Classifier: Programming Language :: Python :: 3.10
Classifier: Programming Language :: Python :: 3.11
Classifier: Topic :: Scientific/Engineering
Classifier: Topic :: Scientific/Engineering :: Artificial Intelligence
Classifier: Topic :: Scientific/Engineering :: Visualization
Requires-Python: >=3.10
Requires-Dist: gradio<6.0,>=4.0
Requires-Dist: markdown>=3.10
Requires-Dist: pygments>=2.19.2
Provides-Extra: dev
Requires-Dist: build; extra == 'dev'
Requires-Dist: twine; extra == 'dev'
